Metadata-Version: 2.1
Name: j2scr
Version: 1.0.1
Summary: Convenience wrapper around Jinja for scripts
Home-page: https://github.com/jonaslb/j2scr
Author: Jonas Lundholm Bertelsen
License: MIT
Platform: UNKNOWN
Classifier: Programming Language :: Python :: 3
Classifier: License :: OSI Approved :: MIT License
Classifier: Operating System :: OS Independent
Requires-Python: >=3.7
